inherit_docstring/__init__.py
inherit_docstring/decorator.py
inherit_docstring/py.typed
inherit_docstring/utils.py
inherit_docstring/version.py
inherit_docstring-0.2.0.dist-info/WHEEL
inherit_docstring-0.2.0.dist-info/METADATA
inherit_docstring-0.2.0.dist-info/RECORD
