Metadata-Version: 2.4
Name: inherit-docstring
Version: 0.2.0
Summary: A python decorator to inherit docstring.
Keywords: docstring,inherit,decorator
Author: rcmdnk
Author-email: rcmdnk <rcmdnk@gmail.com>
License-Expression: Apache-2.0
Classifier: Development Status :: 3 - Alpha
Classifier: Environment :: Console
Classifier: Intended Audience :: Developers
Classifier: Intended Audience :: End Users/Desktop
Classifier: License :: OSI Approved :: Apache Software License
Classifier: Natural Language :: English
Classifier: Operating System :: OS Independent
Classifier: Programming Language :: Python :: 3.9
Classifier: Programming Language :: Python :: 3.10
Classifier: Programming Language :: Python :: 3.11
Classifier: Programming Language :: Python :: 3.12
Classifier: Topic :: Documentation
Requires-Python: >=3.9, <4.0
Project-URL: Homepage, https://github.com/rcmdnk/inherit-docstring
Project-URL: Repository, https://github.com/rcmdnk/inherit-docstring
